edgarpython/__init__.py
edgarpython/exceptions.py
edgarpython/models.py
edgarpython/secapi.py
edgarpython-0.1.0.dist-info/METADATA
edgarpython-0.1.0.dist-info/WHEEL
edgarpython-0.1.0.dist-info/RECORD
